[
   {
   "name": "♥韩美丽的吃货集锦♥",
   "cover": "♥韩美丽的吃货集锦♥/封面.jpg",
   "date": "2020-10",
   "description": "干饭人，干饭魂，干饭才是人上人！",
   "url_name": "♥韩美丽的吃货集锦♥",
   "album": [
       {
           "img_url": "1.jpg",
           "title": "♥韩美丽的吃货集锦♥",
           "describe": "♥干饭人♥"
       },
       {
           "img_url": "https://s3.ax1x.com/2020/12/08/rpr41S.jpg",
           "title": "♥韩美丽的吃货集锦♥",
           "describe": "♥干饭魂♥"
       },
       {
           "img_url": "https://imgchr.com/i/rpr41S",
           "title": "♥韩美丽的吃货集锦♥",
           "describe": "♥干饭才是人上人！♥"
       },
       {
           "img_url": "♥韩美丽的吃货集锦♥/封面.jpg",
           "title": "♥韩美丽的吃货集锦♥",
           "describe": "♥干饭才是人上人！♥"
       }
     ]
   }
 ]